{

	"loc":[
		{	"id":"1",
			"disabled":"1",
			"whydisabled":"由于上学期报名人数太多，未能安排完，故<span style='color:red'><b>这学期不进行报名</b></span>，上学期没有安排到的会在这学期继续安排。",
			"color":"info",
			"name":"广州新图书馆",
			"minintro":"周边环境优美，馆内凉爽舒适<s>，只是熊孩子有点难管</s>",
			"area":"天河区",
			"addr":"广州市天河区珠江东路4号",
			"traffic":"一、乘坐886、886A、293路公交车在冼村路南站下；二、乘坐407路公交车在广州大剧院西门站下；三、乘坐地铁3号线、5号线至珠江新城站下车",
			"works":["整理书籍","维持图书馆内秩序"],
			"times":["周六上午10点到12点30分","周六下午2点30分到5点","周日上午10点到12点30分","周日下午2点30分到5点"],
			"addrE":"http://amap.com/0DDzUM",
			"comm":["①图书馆志愿服务条是当天值日的组长领取且发给各位同学的，所以领完志愿服务条再走哦","②穿着执信校服","③要提前十分钟就在指定地点集中和组长签到。","④同学们要在广州新图书馆西门集合。","⑤如果有特殊情况不能前去服务点的，要自行找替换的同学并告诉本班爱心委员，不然请假、缺席（不包括替换）超过2次的同学会被取消在此志愿点服务的机会"]
		},
		{
			"id":"2",
			"color":"danger",
			"name":"中山图书馆",
			"minintro":"比广图安静得多",
			"area":"越秀区",
			"addr":"广州市越秀区文明路213号",
			"traffic":"乘坐 地铁1号线农讲所站A出口处；乘坐3路 35路 65路 91路 101路 104路 106路 125路 183路 215长线 215路 236路 541路 B8路 广12路 21路 在中山图书馆站或文明路总站下车",
			"works":["整理书籍"],
			"times":["周六上午9点到12点","周六下午2点到5点","周日上午9点到12点","周日下午2点到5点"],
			"addrE":"http://amap.com/0C8zSW",
			"comm":["①地铁农讲所站的A出口集中","②图书馆志愿服务条是当天值日的组长领取且发给各位同学的，所以领完志愿服务条再走哦","③穿着执信校服","④要提前十分钟就在指定地点集中和组长签到。","⑤如果有特殊情况不能前去服务点的，要自行找替换的同学并告诉本班爱心委员，不然请假、缺席（不包括替换）超过2次的同学会被取消在此志愿点服务的机会"]
		},
		{
			"id":"3",
			"color":"success",
			"name":"杨箕地铁站",
			"minintro":"五号线人太多忍无可忍？！想让它变得井然有序么？",
			"area":"越秀区",
			"addr":"杨箕地铁站（地铁一号线和五号线的交接点）",
			"traffic":"乘坐地铁一号线或五号线到杨箕地铁站",
			"works":["客流引导","帮助解决乘客对于路线的疑问"],
			"times":["周六下午3点到5点"],
			"addrE":"http://amap.com/0A0zVm",
			"comm":["①记得平时搭地铁的工作人员都说什么","②穿着执信校服","③提前十分钟就在指定地点集中和组长签到","④如果有特殊情况不能前去服务点的，要自行找替换的同学并告诉本班爱心委员，不然请假、缺席（不包括替换）超过2次的同学会被取消在此志愿点服务的机会"]
		},
		{
			"id":"4",
			"color":"danger",
			"name":"华乐街家庭综合服务中心",
			"minintro":"想锻炼自己的口才为他人讲解垃圾分类知识吗？想辅导小学生的学习吗？…除此之外，还有更多有趣的不定期大型活动噢～",
			"area":"越秀区",
			"addr":"广州市淘金路176号对面",
			"traffic":"乘坐482路到淘金路站下",
			"works":["义教","整理清洁","不定期大型活动","垃圾分类讲解"],
			"times":["周六上午9点到11点"],
			"addrE":"http://amap.com/0F1A0G",
			"comm":["①地点比较难找，建议自带手机导航","②穿着执信校服","③提前十分钟就在指定地点集中和组长签到","④如果有特殊情况不能前去服务点的，要自行找替换的同学并告诉本班爱心委员，不然请假、缺席（不包括替换）超过2次的同学会被取消在此志愿点服务的机会"]
		},
		{
			"id":"5",
			"color":"warning",
			"name":"广州至灵学校",
			"minintro":"体验学校风格，帮老师授课，陪小朋友们玩耍！",
			"area":"越秀区",
			"addr":"广州麓景西狮带岗中6号",
			"traffic":"①乘坐 706路 ,190路 ,夜32路 ,544路 ,546路 ,76A路 ,547路 ,76路 ,高峰快线67路在广州电大麓湖校区站下车；②打的",
			"works":["辅助老师的教学","小朋友们运动课活动"],
			"times":["周六上午9点到11点","周日上午9点到11点"],
			"addrE":"http://amap.com/011zWe",
			"comm":["①地点比较难找，建议自带手机导航","②穿着执信校服","③提前十分钟就在指定地点集中和组长签到","④如果有特殊情况不能前去服务点的，要自行找替换的同学并告诉本班爱心委员，不然请假、缺席（不包括替换）超过2次的同学会被取消在此志愿点服务的机会"]
		},
		{
			"id":"6",
			"color":"info",
			"name":"东山福利院",
			"minintro":"展现你的话唠才能~<br>P.S.两周安排一次志愿活动",
			"area":"荔湾区",
			"addr":"文明路224号（中山图书馆正对面）",
			"traffic":"①乘坐 3路 B8路 12路 夜21路 35路 夜36路 夜39路 42路 65路 夜69路 91路 101路 104路 106路 125路 183路 215路 215路长线 541路到中山图书馆站下车；②乘坐地铁1号线到农讲所A出口",
			"works":["陪老人聊天"],
			"times":["周六上午9:00-10:30"],
			"addrE":"http://f.amap.com/0B115Nn",
			"comm":["①会粤语最好，不会也没有关系:D","②本志愿点隔周安排一次，即每月两次","③穿着执信校服","④提前十分钟就在指定地点集中和组长签到","⑤如果有特殊情况不能前去服务点的，要自行找替换的同学并告诉本班爱心委员，不然请假、缺席（不包括替换）超过2次的同学会被取消在此志愿点服务的机会"]
		}
	]
}
